[{"cines":["https://homernetwork.github.io/vocabulary/audiences/Cinema"],"cine":["https://homernetwork.github.io/vocabulary/audiences/Cinema"],"cin":["https://homernetwork.github.io/vocabulary/audiences/Cinema"],"ci":["https://homernetwork.github.io/vocabulary/audiences/Cinema"],"c":["https://homernetwork.github.io/vocabulary/audiences/Cinema","https://homernetwork.github.io/vocabulary/audiences/Cinema_house"],"ines":["https://homernetwork.github.io/vocabulary/audiences/Cinema"],"ine":["https://homernetwork.github.io/vocabulary/audiences/Cinema"],"in":["https://homernetwork.github.io/vocabulary/audiences/Cinema"],"i":["https://homernetwork.github.io/vocabulary/audiences/Cinema","https://homernetwork.github.io/vocabulary/audiences/Cinema_house"],"nes":["https://homernetwork.github.io/vocabulary/audiences/Cinema"],"ne":["https://homernetwork.github.io/vocabulary/audiences/Cinema"],"n":["https://homernetwork.github.io/vocabulary/audiences/Cinema"],"es":["https://homernetwork.github.io/vocabulary/audiences/Cinema"],"e":["https://homernetwork.github.io/vocabulary/audiences/Cinema","https://homernetwork.github.io/vocabulary/audiences/Cinema_house","https://homernetwork.github.io/vocabulary/audiences/Teatro","https://homernetwork.github.io/vocabulary/audiences/Terraza"],"s":["https://homernetwork.github.io/vocabulary/audiences/Cinema","https://homernetwork.github.io/vocabulary/audiences/Cinema_house"],"coliseum":["https://homernetwork.github.io/vocabulary/audiences/Cinema_house"],"coliseu":["https://homernetwork.github.io/vocabulary/audiences/Cinema_house"],"colise":["https://homernetwork.github.io/vocabulary/audiences/Cinema_house"],"colis":["https://homernetwork.github.io/vocabulary/audiences/Cinema_house"],"coli":["https://homernetwork.github.io/vocabulary/audiences/Cinema_house"],"col":["https://homernetwork.github.io/vocabulary/audiences/Cinema_house"],"co":["https://homernetwork.github.io/vocabulary/audiences/Cinema_house"],"oliseum":["https://homernetwork.github.io/vocabulary/audiences/Cinema_house"],"oliseu":["https://homernetwork.github.io/vocabulary/audiences/Cinema_house"],"olise":["https://homernetwork.github.io/vocabulary/audiences/Cinema_house"],"olis":["https://homernetwork.github.io/vocabulary/audiences/Cinema_house"],"oli":["https://homernetwork.github.io/vocabulary/audiences/Cinema_house"],"ol":["https://homernetwork.github.io/vocabulary/audiences/Cinema_house"],"o":["https://homernetwork.github.io/vocabulary/audiences/Cinema_house","https://homernetwork.github.io/vocabulary/audiences/Teatro"],"liseum":["https://homernetwork.github.io/vocabulary/audiences/Cinema_house"],"liseu":["https://homernetwork.github.io/vocabulary/audiences/Cinema_house"],"lise":["https://homernetwork.github.io/vocabulary/audiences/Cinema_house"],"lis":["https://homernetwork.github.io/vocabulary/audiences/Cinema_house"],"li":["https://homernetwork.github.io/vocabulary/audiences/Cinema_house"],"l":["https://homernetwork.github.io/vocabulary/audiences/Cinema_house"],"iseum":["https://homernetwork.github.io/vocabulary/audiences/Cinema_house"],"iseu":["https://homernetwork.github.io/vocabulary/audiences/Cinema_house"],"ise":["https://homernetwork.github.io/vocabulary/audiences/Cinema_house"],"is":["https://homernetwork.github.io/vocabulary/audiences/Cinema_house"],"seum":["https://homernetwork.github.io/vocabulary/audiences/Cinema_house"],"seu":["https://homernetwork.github.io/vocabulary/audiences/Cinema_house"],"se":["https://homernetwork.github.io/vocabulary/audiences/Cinema_house"],"eum":["https://homernetwork.github.io/vocabulary/audiences/Cinema_house"],"eu":["https://homernetwork.github.io/vocabulary/audiences/Cinema_house"],"um":["https://homernetwork.github.io/vocabulary/audiences/Cinema_house"],"u":["https://homernetwork.github.io/vocabulary/audiences/Cinema_house"],"m":["https://homernetwork.github.io/vocabulary/audiences/Cinema_house"],"teatro":["https://homernetwork.github.io/vocabulary/audiences/Teatro"],"teatr":["https://homernetwork.github.io/vocabulary/audiences/Teatro"],"teat":["https://homernetwork.github.io/vocabulary/audiences/Teatro"],"tea":["https://homernetwork.github.io/vocabulary/audiences/Teatro"],"te":["https://homernetwork.github.io/vocabulary/audiences/Teatro","https://homernetwork.github.io/vocabulary/audiences/Terraza"],"t":["https://homernetwork.github.io/vocabulary/audiences/Teatro","https://homernetwork.github.io/vocabulary/audiences/Terraza"],"eatro":["https://homernetwork.github.io/vocabulary/audiences/Teatro"],"eatr":["https://homernetwork.github.io/vocabulary/audiences/Teatro"],"eat":["https://homernetwork.github.io/vocabulary/audiences/Teatro"],"ea":["https://homernetwork.github.io/vocabulary/audiences/Teatro"],"atro":["https://homernetwork.github.io/vocabulary/audiences/Teatro"],"atr":["https://homernetwork.github.io/vocabulary/audiences/Teatro"],"at":["https://homernetwork.github.io/vocabulary/audiences/Teatro"],"a":["https://homernetwork.github.io/vocabulary/audiences/Teatro","https://homernetwork.github.io/vocabulary/audiences/Terraza"],"tro":["https://homernetwork.github.io/vocabulary/audiences/Teatro"],"tr":["https://homernetwork.github.io/vocabulary/audiences/Teatro"],"ro":["https://homernetwork.github.io/vocabulary/audiences/Teatro"],"r":["https://homernetwork.github.io/vocabulary/audiences/Teatro","https://homernetwork.github.io/vocabulary/audiences/Terraza"],"terraza":["https://homernetwork.github.io/vocabulary/audiences/Terraza"],"terraz":["https://homernetwork.github.io/vocabulary/audiences/Terraza"],"terra":["https://homernetwork.github.io/vocabulary/audiences/Terraza"],"terr":["https://homernetwork.github.io/vocabulary/audiences/Terraza"],"ter":["https://homernetwork.github.io/vocabulary/audiences/Terraza"],"erraza":["https://homernetwork.github.io/vocabulary/audiences/Terraza"],"erraz":["https://homernetwork.github.io/vocabulary/audiences/Terraza"],"erra":["https://homernetwork.github.io/vocabulary/audiences/Terraza"],"err":["https://homernetwork.github.io/vocabulary/audiences/Terraza"],"er":["https://homernetwork.github.io/vocabulary/audiences/Terraza"],"rraza":["https://homernetwork.github.io/vocabulary/audiences/Terraza"],"rraz":["https://homernetwork.github.io/vocabulary/audiences/Terraza"],"rra":["https://homernetwork.github.io/vocabulary/audiences/Terraza"],"rr":["https://homernetwork.github.io/vocabulary/audiences/Terraza"],"raza":["https://homernetwork.github.io/vocabulary/audiences/Terraza"],"raz":["https://homernetwork.github.io/vocabulary/audiences/Terraza"],"ra":["https://homernetwork.github.io/vocabulary/audiences/Terraza"],"aza":["https://homernetwork.github.io/vocabulary/audiences/Terraza"],"az":["https://homernetwork.github.io/vocabulary/audiences/Terraza"],"za":["https://homernetwork.github.io/vocabulary/audiences/Terraza"],"z":["https://homernetwork.github.io/vocabulary/audiences/Terraza"]},{},{},{},{},{},{},{},{}]